sure_trans/__init__.py
sure_trans/__main__.py
sure_trans/sure_trans.py
sure_trans-0.1.0a0.dist-info/entry_points.txt
sure_trans-0.1.0a0.dist-info/LICENSE
sure_trans-0.1.0a0.dist-info/WHEEL
sure_trans-0.1.0a0.dist-info/METADATA
sure_trans-0.1.0a0.dist-info/RECORD
